{"noMoreComments": true, "cursorEnd": 0, "id": "9685000", "comments": [{"postBy": {"location": "", "utc": 1537696711000, "level": 0, "avatar": "http://filestoresg1.beetalkmobile.com:8081/file/-612869954973249173", "name": "\u884c\u4e5e\u4eba"}, "content": "\u59b3\u662f\u8aaa\u8001\u9f20\u4fbf\u79d8\u7684\u554f\u984c\u53ef\u4ee5\u8acb\u6559\u59b3\u55ce\uff1f\u9084\u662f\u8b93\u8001\u9f20\u7626\uff1f", "urls": [], "replies": {"first": [], "last": [], "noMoreReplies": true}, "images": ["http://filestoresg1.beetalkmobile.com:8081/file/cbf69c908474460449d5c0af3cb4085f"], "id": 97450510}, {"postBy": {"location": "\u65b0\u5317\u5e02\u00b7\u53f0\u7063", "utc": 1537697392000, "level": 0, "avatar": "http://filestoresg1.beetalkmobile.com:8081/file/3219567983941800312", "name": "\u6d3e\u5927\u73ca"}, "content": "\u4f60\u6709\u8001\u9f20\u55ce\uff1f\ud83e\udd23", "urls": [], "replies": {"first": [{"content": "\u8001\u9f20\u53ea\u611b\u5927\u7c73\ud83d\ude06\ud83d\ude06\ud83d\ude06", "reply": "", "id": 60019589, "name": "\u884c\u4e5e\u4eba"}, {"content": "\ud83d\ude06", "reply": "", "id": 60019941, "name": "\u6d3e\u5927\u73ca"}], "last": [], "noMoreReplies": true}, "images": [], "id": 97451099}]}
