{"noMoreComments": true, "cursorEnd": 0, "id": "9477902", "comments": [{"postBy": {"location": "\u6843\u5712\u5e02\u00b7\u53f0\u7063", "utc": 1536053414000, "level": 0, "avatar": "http://filestoresg1.beetalkmobile.com:8081/file/-2877915590927407866", "name": "\u2606\u2606\u2606\u2606\u2606"}, "content": "\u56e0\u4eba\u800c\u7570\uff0c\u5404\u5176\u6240\u601d", "urls": [], "replies": {"first": [], "last": [], "noMoreReplies": true}, "images": [], "id": 96071529}, {"postBy": {"location": "\u53f0\u7063", "utc": 1536176717000, "level": 0, "avatar": "http://filestoresg1.beetalkmobile.com:8081/file/308453717677946429", "name": "\u2022\u00b0\u5361\u54c7\u4f0a\u00b0\u2022"}, "content": "\u4eba\u4e0d\u7528\u592a\u5e25\u592a\u7f8e<br />\u6bcf\u5929\u770b\u4e0d\u81a9\u624d\u662f\u6700\u5be6\u5728\u7684", "urls": [], "replies": {"first": [], "last": [], "noMoreReplies": true}, "images": [], "id": 96180963}, {"postBy": {"location": "\u65b0\u5317\u5e02\u00b7\u53f0\u7063", "utc": 1536205906000, "level": 0, "avatar": "http://filestoresg1.beetalkmobile.com:8081/file/-8689975833402491890", "name": "ziying"}, "content": "\u770b\u6210\u5916\u570b\u4eba\u4e86\u634f \u600e\u9ebc\u8fa6", "urls": [], "replies": {"first": [], "last": [], "noMoreReplies": true}, "images": [], "id": 96199505}, {"postBy": {"location": "\u53f0\u5357\u5e02\u00b7\u53f0\u7063", "utc": 1536233601000, "level": 0, "avatar": "http://filestoresg1.beetalkmobile.com:8081/file/2", "name": "User blocked"}, "content": "\u4f60\u597d\u55ce\uff1f\u6211\u4f4f\u53f0\u5357\u5e02\uff0c\u6211\u662f\u7f8e\u5bb9\u5e2b", "urls": [], "replies": {"first": [], "last": [], "noMoreReplies": true}, "images": [], "id": 96222835}, {"postBy": {"location": "\u6843\u5712\u5e02\u00b7\u53f0\u7063", "utc": 1536331035000, "level": 0, "avatar": "http://filestoresg1.beetalkmobile.com:8081/file/8804520802931076093", "name": "\u6211\u662f\u7b28\u840d"}, "content": "\u4f60\u4ec0\u4e48\u5e25\u6c92\u6709\u4ea4\u5973\u670b\u53cb", "urls": [], "replies": {"first": [], "last": [], "noMoreReplies": true}, "images": [], "id": 96308762}, {"postBy": {"location": "\u53f0\u4e2d\u5e02\u00b7\u53f0\u7063", "utc": 1536422158000, "level": 0, "avatar": "http://filestoresg1.beetalkmobile.com:8081/file/-2645498639868658506", "name": "\u522a\u4e86"}, "content": "\u7b97\u5e25\u54e5", "urls": [], "replies": {"first": [], "last": [], "noMoreReplies": true}, "images": [], "id": 96387837}, {"postBy": {"location": "", "utc": 1536473695000, "level": 0, "avatar": "http://filestoresg1.beetalkmobile.com:8081/file/-3405037962329997312", "name": "\u5996\u9b54\u9b3c\u602a\u901f\u901f\u96e2\u958b"}, "content": "\u554a\u4f60\u90fd\u77e5\u9053\u81ea\u5df1\u4e0d\u662f\u5e25\u54e5\u4e86 \u5e79\u561b\u9084po\u5728\u578b\u7537\u5e25\u54e5\u7248\uff1f", "urls": [], "replies": {"first": [], "last": [], "noMoreReplies": true}, "images": [], "id": 96427725}]}
