{"noMoreComments": true, "cursorEnd": 0, "id": "9486141", "comments": [{"postBy": {"location": "\u6843\u5712\u5e02\u00b7\u53f0\u7063", "utc": 1536001787000, "level": 0, "avatar": "http://filestoresg1.beetalkmobile.com:8081/file/-21094105126754035", "name": "\u9673\u5764\u5c71"}, "content": "\u52a0\u52a0<br />", "urls": [], "replies": {"first": [{"content": "\u7559\u500b\u540d\u5b57\u5504 \u2795\u4e86\u624d\u77e5\u9053\u662f\u8ab0", "reply": "", "id": 59436280, "name": "\u5446\u5446der\u7b28\u86cb"}, {"content": "\u61c9\u8a72\u662fpaps010640", "reply": "", "id": 59466366, "name": "\u9673\u5764\u5c71"}], "last": [], "noMoreReplies": true}, "images": [], "id": 96037269}, {"postBy": {"location": "", "utc": 1536030562000, "level": 0, "avatar": "http://filestoresg1.beetalkmobile.com:8081/file/6588042779793950466", "name": "\ud83d\udc2f"}, "content": "\u4e00\u8d77\u73a9\u554a", "urls": [], "replies": {"first": [{"content": "\u7559\u500b\u540d\u5b57\u5504 \u2795\u4e86\u624d\u77e5\u9053\u662f\u8ab0", "reply": "", "id": 59436290, "name": "\u5446\u5446der\u7b28\u86cb"}, {"content": "\u5bf6\u4ea86\u865f", "reply": "", "id": 59466389, "name": "\ud83d\udc2f"}], "last": [], "noMoreReplies": true}, "images": [], "id": 96053460}, {"postBy": {"location": "\u53f0\u7063", "utc": 1536075186000, "level": 0, "avatar": "http://filestoresg1.beetalkmobile.com:8081/file/-5730436899091460746", "name": "remus"}, "content": "\u840c\u65b0\u4e48\u4e48\u5660", "urls": [], "replies": {"first": [], "last": [], "noMoreReplies": true}, "images": [], "id": 96094961}, {"postBy": {"location": "\u81fa\u7063\u7701\u00b7\u53f0\u7063", "utc": 1536077909000, "level": 0, "avatar": "http://filestoresg1.beetalkmobile.com:8081/file/-4569210783473668600", "name": "Sean"}, "content": "++ ID:\u767d\u718a\u5566", "urls": [], "replies": {"first": [], "last": [], "noMoreReplies": true}, "images": [], "id": 96098447}, {"postBy": {"location": "\u53f0\u4e2d\u5e02\u00b7\u53f0\u7063", "utc": 1536131431000, "level": 0, "avatar": "http://filestoresg1.beetalkmobile.com:8081/file/-7057496855798826397", "name": "nnnnn"}, "content": "\u53ea\u73a9\u7b2c\u4e00\u4eba\u7a31\u53ef\u55ce\uff1f", "urls": [], "replies": {"first": [], "last": [], "noMoreReplies": true}, "images": [], "id": 96136994}, {"postBy": {"location": "\u53f0\u7063", "utc": 1536135231000, "level": 0, "avatar": "http://filestoresg1.beetalkmobile.com:8081/file/91362835109148259", "name": "\ud83d\uddef\u98c4\ud83d\udcad\u2026\ud83d\udc40"}, "content": "\u52a0\u52a0    id.\u907a\u61be\u6210\u5c31\u4e86\u73cd\u60dc", "urls": [], "replies": {"first": [], "last": [], "noMoreReplies": true}, "images": [], "id": 96140086}, {"postBy": {"location": "\u9ad8\u96c4\u5e02\u00b7\u53f0\u7063", "utc": 1536199581000, "level": 0, "avatar": "http://filestoresg1.beetalkmobile.com:8081/file/-8598823020883020632", "name": "\ud83d\udc7b\ud83d\udc7b\ud83d\udc7b"}, "content": "IO skr\u6f02\u6cca\u7537\u5b50", "urls": [], "replies": {"first": [], "last": [], "noMoreReplies": true}, "images": [], "id": 96193920}, {"postBy": {"location": "", "utc": 1536384142000, "level": 0, "avatar": "http://filestoresg1.beetalkmobile.com:8081/file/1586167578985746433", "name": "\u7ae5"}, "content": "\u904a\u6232\u540d\u5b57 \u5c0f\u59d0\u59d0\u51e0\u5c81\u4f4f\u54ea\ud83d\ude02", "urls": [], "replies": {"first": [], "last": [], "noMoreReplies": true}, "images": [], "id": 96351400}, {"postBy": {"location": "\u65b0\u5317\u5e02\u00b7\u53f0\u7063", "utc": 1536406938000, "level": 0, "avatar": "http://filestoresg1.beetalkmobile.com:8081/file/-3243366882719657944", "name": "Weihao   \uff08181"}, "content": "\u4e00\u8d77\u958b\u5fc3\u73a9\u554a\ud83d\ude01", "urls": [], "replies": {"first": [], "last": [], "noMoreReplies": true}, "images": [], "id": 96370439}, {"postBy": {"location": "", "utc": 1536587633000, "level": 0, "avatar": "http://filestoresg1.beetalkmobile.com:8081/file/-8124030832279231956", "name": "\u5446\u5446der\u7b28\u86cb"}, "content": "\u81ea\u5df1\u52a0\u6211\u54e6", "urls": [], "replies": {"first": [], "last": [], "noMoreReplies": true}, "images": [], "id": 96527723}]}
