{"noMoreComments": true, "cursorEnd": 0, "id": "9740559", "comments": [{"postBy": {"location": "\u65b0\u5317\u5e02\u00b7\u53f0\u7063", "utc": 1538166654000, "level": 0, "avatar": "http://filestoresg1.beetalkmobile.com:8081/file/-3229031431500524959", "name": "\u2721\u6634\u5bbf\u661f\u2721"}, "content": "\u9019\u9ebc\u665a\u4e86\u2026\u2026\u4e0d\u5c0d\uff0c\u5df2\u7d93\u65e9\u4e0a\u4e86<br /><br /><br />\u9019\u9ebc\u65e9\u8036", "urls": [], "replies": {"first": [{"content": "\u5c0d\u554a~", "reply": "", "id": 60162098, "name": "\ud83d\udc52Palomababy \ud83d\udd4a"}], "last": [], "noMoreReplies": true}, "images": [], "id": 97792625}, {"postBy": {"location": "\u65b0\u5317\u5e02\u00b7\u53f0\u7063", "utc": 1538169618000, "level": 0, "avatar": "http://filestoresg1.beetalkmobile.com:8081/file/5257867924923529112", "name": "\u827e\u723e\u535a"}, "content": "\u771f\u7684\u6709\u9ede\u65e9", "urls": [], "replies": {"first": [], "last": [], "noMoreReplies": true}, "images": [], "id": 97793868}, {"postBy": {"location": "", "utc": 1538177399000, "level": 0, "avatar": "http://filestoresg1.beetalkmobile.com:8081/file/7563880241604127232", "name": "\u50bb\u903c\u7cbe\u795e~\ud83e\udd18\ud83c\udffc"}, "content": "\u534a\u591c\u2026\u2026", "urls": [], "replies": {"first": [], "last": [], "noMoreReplies": true}, "images": [], "id": 97797296}, {"postBy": {"location": "\u53f0\u5317\u5e02\u00b7\u53f0\u7063", "utc": 1538190339000, "level": 0, "avatar": "http://filestoresg1.beetalkmobile.com:8081/file/3370657358894508950", "name": "David \u5927\u885b"}, "content": "\u6211\u4e5f\u8981\u5403\u2026\u2026 \u51b0", "urls": [], "replies": {"first": [], "last": [], "noMoreReplies": true}, "images": [], "id": 97805463}, {"postBy": {"location": "\u9ad8\u96c4\u5e02\u00b7\u53f0\u7063", "utc": 1538205068000, "level": 0, "avatar": "http://filestoresg1.beetalkmobile.com:8081/file/-6932111824938331375", "name": "\u5566\u5566\u5566"}, "content": "\u90a3\u500b\u51b0\u662f\u4e0d\u932f\u5403 \u53ef\u62ff\u4f86\u7576\u65e9\u9910\u2026\u2026\u2026\u2026\uff1f\uff1f\uff1f\uff1f\uff1f<br /><br />\u73fe\u5728\u662f\u51cc\u6668\u4e09\u9ede\u9418\uff5e\uff0812\u5c0f\u6642\u524d", "urls": [], "replies": {"first": [{"content": "\u9ede\u5fc3\u4e0d\u5206\u6642\u6bb5", "reply": "", "id": 60162092, "name": "\ud83d\udc52Palomababy \ud83d\udd4a"}, {"content": "\u539f\u4f86\u662f\u9ede\u5fc3\u963f\uff5e\u90a3\u5c31\u6c92\u95dc\u4fc2\u4e86\u2026\u2026\u2026\u2026\u534a\u591c\u4e09\u9ede\u662f\u5565\u9ede\u5fc3\u963f\uff1f\uff01\ud83d\ude02\ud83d\ude02\ud83d\ude02\ud83d\ude02", "reply": "\ud83d\udc52Palomababy \ud83d\udd4a", "id": 60170755, "name": "\u5566\u5566\u5566"}], "last": [], "noMoreReplies": true}, "images": [], "id": 97815697}]}
