{"noMoreComments": true, "cursorEnd": 0, "id": "9201787", "comments": [{"postBy": {"location": "\u53f0\u5317\u5e02\u00b7\u53f0\u7063", "utc": 1533570401000, "level": 0, "avatar": "http://filestoresg1.beetalkmobile.com:8081/file/-2096005606026919623", "name": "\u4eba\u8518\u6012\u6d6a\u6298\u5b78"}, "content": "\u96e3\u5f97\u6709\u767b\u5c71\u7cfb\u7f8e\u5973", "urls": [], "replies": {"first": [], "last": [], "noMoreReplies": true}, "images": [], "id": 93988031}, {"postBy": {"location": "\u53f0\u5317\u5e02\u00b7\u53f0\u7063", "utc": 1534858849000, "level": 0, "avatar": "http://filestoresg1.beetalkmobile.com:8081/file/-7066452376180168667", "name": "\u6625\u5206"}, "content": "\u597d\u53b2\u5bb3\u554a\ud83d\udc4d", "urls": [], "replies": {"first": [], "last": [], "noMoreReplies": true}, "images": [], "id": 95091473}, {"postBy": {"location": "\u53f0\u5357\u5e02\u00b7\u53f0\u7063", "utc": 1535162596000, "level": 0, "avatar": "http://filestoresg1.beetalkmobile.com:8081/file/1926781991109838601", "name": "\u5927\u982d"}, "content": "\u7167\u7247\u90fd\u59b3\u81ea\u62cd\u55ce\uff01\uff1f<br />\u597d\u5f37\u554a\u554a", "urls": [], "replies": {"first": [], "last": [], "noMoreReplies": true}, "images": [], "id": 95344149}]}
