{"noMoreComments": true, "cursorEnd": 0, "id": "9650489", "comments": [{"postBy": {"location": "\u53f0\u5317\u5e02\u00b7\u53f0\u6e7e", "utc": 1537411093000, "level": 0, "avatar": "http://filestoresg1.beetalkmobile.com:8081/file/5711827667621779049", "name": "BeeTalk User"}, "content": "\u2665\u54c8\u56c9", "urls": [], "replies": {"first": [{"content": "\u55e8\uff5e", "reply": "", "id": 59919796, "name": "\u566f\u566f\u2661"}], "last": [], "noMoreReplies": true}, "images": [], "id": 97211365}, {"postBy": {"location": "", "utc": 1537413896000, "level": 0, "avatar": "http://filestoresg1.beetalkmobile.com:8081/file/6762928897842623233", "name": "\u6fa4\u6fa4"}, "content": "\u60f3\u61c9\u5fb5 \u53ef\u662f\u597d\u9059\u9060\ud83d\ude44\ud83d\ude44\ud83d\ude44", "urls": [], "replies": {"first": [{"content": "\u596a\u90600.0", "reply": "", "id": 59919803, "name": "\u566f\u566f\u2661"}], "last": [{"content": "\u6211\u5f70\u5316\u6b38\ud83d\ude14", "reply": "", "id": 59920074, "name": "\u6fa4\u6fa4"}, {"content": "\u611b\uff0c\u4e0d\u6015\u9060", "reply": "", "id": 59924592, "name": "\u66e6"}], "noMoreReplies": true}, "images": [], "id": 97213587}, {"postBy": {"location": "", "utc": 1537492470000, "level": 0, "avatar": "http://filestoresg1.beetalkmobile.com:8081/file/2052228563852360194", "name": "Hush"}, "content": "\u55e8\uff5e", "urls": [], "replies": {"first": [], "last": [], "noMoreReplies": true}, "images": [], "id": 97278294}]}
