{"noMoreComments": true, "cursorEnd": 0, "id": "9107766", "comments": [{"postBy": {"location": "\u53f0\u4e2d\u5e02\u00b7\u53f0\u7063", "utc": 1532614383000, "level": 0, "avatar": "http://filestoresg1.beetalkmobile.com:8081/file/5038063447850517960", "name": "\u524d\u8f29\u554a"}, "content": "\u52a0\u6cb9\u5427", "urls": [], "replies": {"first": [{"content": "\u8ddf\u8ab0\u52a0\u6cb9 ?", "reply": "", "id": 58348053, "name": "\u65b9 \u8001\u5e2b"}], "last": [{"content": "\u9019\u6c92\u7528\uff0c\u7b11\u53e3\u5e38\u958b\u5c31\u53ef\u4ee5\u3002", "reply": "\u524d\u8f29\u554a", "id": 58348573, "name": "\u65b9 \u8001\u5e2b"}, {"content": "\u8a31\u7d14\u7f8e\u7b11\u53e3\u5e38\u958b\uff0c\u6211\u597d\u50cf\u4e0d\u89ba\u5f97\u6709\u7528", "reply": "", "id": 58675595, "name": "StanleyLin"}], "noMoreReplies": false}, "images": [], "id": 93183882}, {"postBy": {"location": "\u6843\u5712\u5e02\u00b7\u53f0\u7063", "utc": 1532616421000, "level": 0, "avatar": "http://filestoresg1.beetalkmobile.com:8081/file/8805201378540152158", "name": "Se7eN"}, "content": "\u771f\u7684 \u723a\u5b6b\u6200 \u4e5f\u662f", "urls": [], "replies": {"first": [{"content": "\u9019\u592a\u50b7\u773c\u7403\u4e86 ", "reply": "", "id": 58348071, "name": "\u65b9 \u8001\u5e2b"}], "last": [{"content": "\u723a\u723a\u662f\u8eab\u65c1\u6709\u500b\u5e7c\u9f52\u5b6b\u5973\u5728\u65c1\u908a\u6703\u5bb3\u7f9e\u800c\u5df2\u5427\uff1f\u54c8\u54c8\u5e79\u561b\u628a\u723a\u5b6b\u6200\u60f3\u7684\u90a3\u9ebc\u90aa\u60e1  \u9019\u6a23\u4e0d\u597d\u5594\uff01\u9ad2\u9ad2", "reply": "\u65b9 \u8001\u5e2b", "id": 58672248, "name": "Elena(\u7fce)"}, {"content": "\u723a\u5b6b\"\u6200\" \u672c\u8eab\u5c31\u5f88\u90aa\u60e1\u4e86", "reply": "Elena(\u7fce)", "id": 58673205, "name": "\u65b9 \u8001\u5e2b"}], "noMoreReplies": false}, "images": ["http://filestoresg1.beetalkmobile.com:8081/file/f6c6ac0d1133df134a0098e8fa1ad324"], "id": 93186524}, {"postBy": {"location": "", "utc": 1532617170000, "level": 0, "avatar": "http://filestoresg1.beetalkmobile.com:8081/file/7563880241604127232", "name": "\u50bb\u903c\u7cbe\u795e~\ud83e\udd18\ud83c\udffc"}, "content": "\u524d\u63d0\u2026\u2026\u8981\u6709\u5f97\u8ac7\ud83e\udd14", "urls": [], "replies": {"first": [{"content": "\u4f60\u4e5f\u60f3\u723a\u5b6b\u6200? \u53ef\u80fd\u8981\u518d\u904e\u5e7e\u5e74\u5594\u2026", "reply": "", "id": 58348623, "name": "\u65b9 \u8001\u5e2b"}, {"content": "\u4e0d\u4e86\u2026\u2026\u9019\u6a23\u5c31\u597d\u2026\u2026\u611f\u8b1d\u5927\u5fb7\uff01", "reply": "\u65b9 \u8001\u5e2b", "id": 58348736, "name": "\u50bb\u903c\u7cbe\u795e~\ud83e\udd18\ud83c\udffc"}], "last": [], "noMoreReplies": true}, "images": [], "id": 93187526}, {"postBy": {"location": "\u53f0\u7063", "utc": 1532617798000, "level": 0, "avatar": "http://filestoresg1.beetalkmobile.com:8081/file/737991129922283019", "name": "\u5225\u540d"}, "content": "\u9019\u6a23\u7684\u6200\u4eba,\u5176\u5be6\u986f\u800c\u6613\u898b\u3002<br />\u6211\u7528\u7334\u5b50\u8aaa\u660e,\u53ea\u70ba\u4e86\u4e92\u88dc\u3002", "urls": [], "replies": {"first": [{"content": "\u7334\u5b50??  \u8aaa\u9ede\u4eba\u8a71\u597d\u55ce\uff01", "reply": "", "id": 58349536, "name": "\u65b9 \u8001\u5e2b"}], "last": [{"content": "\u771f\u76f8\u6c38\u9060\u662f\u771f\u76f8\u3002", "reply": "\u65b9 \u8001\u5e2b", "id": 58349899, "name": "\u5225\u540d"}, {"content": "\u56e0\u70ba\u300c\u611b\u300d\uff0c\u5e74\u7d00\u4e0d\u662f\u554f\u984c", "reply": "\u5225\u540d", "id": 58353694, "name": "\u65b9 \u8001\u5e2b"}], "noMoreReplies": false}, "images": [], "id": 93188294}, {"postBy": {"location": "\u53f0\u5357\u5e02\u00b7\u53f0\u7063", "utc": 1532619436000, "level": 0, "avatar": "http://filestoresg1.beetalkmobile.com:8081/file/-6900591047355768636", "name": "\u5dee\u4e0d\u591a\u5148\u751f"}, "content": "\u8a31\u7d14\u7f8e.....<br /><br />\u53e3\u888b\u7684\u6df1\u5ea6\u6c7a\u5b9a\u4e00\u5207", "urls": [], "replies": {"first": [{"content": "\u9019\u53e5\u592a\u7cbe\u5c41\u4e86\uff01", "reply": "", "id": 58349568, "name": "\u65b9 \u8001\u5e2b"}], "last": [], "noMoreReplies": true}, "images": [], "id": 93190267}, {"postBy": {"location": "\u53f0\u7063", "utc": 1532624323000, "level": 0, "avatar": "http://filestoresg1.beetalkmobile.com:8081/file/-2691260307791060347", "name": "\u6708\u591c\u7434\u4eba"}, "content": "\u5378\u599d\u2026\u2026<br />\u8eab\u5206\u8b49\u62ff\u51fa\u4f86\u2026\u2026", "urls": [], "replies": {"first": [{"content": "\u6211\u4e5f\u60f3\u770b\u5979\u5378\u599d ^^ ", "reply": "", "id": 58353663, "name": "\u65b9 \u8001\u5e2b"}, {"content": "\u5378\u599d\u99ac\u4e0a\u5c112\u516c\u65a4", "reply": "", "id": 58409528, "name": "\u5fd8\u4e86"}], "last": [], "noMoreReplies": true}, "images": [], "id": 93195856}, {"postBy": {"location": "\u53f0\u7063", "utc": 1532733406000, "level": 0, "avatar": "http://filestoresg1.beetalkmobile.com:8081/file/7440992221981797282", "name": "\u963fRe"}, "content": "\u9b54\u5973\u7684\u689d\u4ef6\u7e8c\u96c6", "urls": [], "replies": {"first": [{"content": "\u90a3\u53ef\u662f\u83dc\u83dc\u5b50\u914d\u7027\u6fa4\u79c0\u660e\u8036\uff01\n\u8ac7\u4f55\u5bb9\u6613", "reply": "", "id": 58418644, "name": "\u4ef0\u671b\u7684\u9ad8\u5ea6"}], "last": [], "noMoreReplies": true}, "images": [], "id": 93283548}, {"postBy": {"location": "\u53f0\u5317\u5e02\u00b7\u53f0\u7063", "utc": 1532765519000, "level": 0, "avatar": "http://filestoresg1.beetalkmobile.com:8081/file/-3385915262418180408", "name": "\u6c5f\u897f\u5927\u53d4"}, "content": "\u7537\u7684\u5c31\u9ebb\u7169\u4f60<br />\u5e6b\u6211\u89e3\u6c7a\u4e86", "urls": [], "replies": {"first": [{"content": "\u7537\u7684\u984f\u503c\u4e5f\u5f88\u9ad8\u554a\uff01", "reply": "", "id": 58390285, "name": "wenchinghuang"}], "last": [], "noMoreReplies": true}, "images": [], "id": 93308894}, {"postBy": {"location": "\u9ad8\u96c4\u5e02\u00b7\u53f0\u7063", "utc": 1532768072000, "level": 0, "avatar": "http://filestoresg1.beetalkmobile.com:8081/file/-4591743069570333983", "name": "wenchinghuang"}, "content": "\u904e\u500b\u5341\u5e74\uff0c<br />\u6015\u5973\u65b9\u6703\u6bd4\u8f03\u6c92\u6709\u5b89\u5168\u611f\u4e86\u3002", "urls": [], "replies": {"first": [{"content": "\u904e10\u5e74\u5f8c\u5c31\u4e0d\u662f\u770b\u76ae\u76f8\u4e86\u3002", "reply": "", "id": 58391310, "name": "\u65b9 \u8001\u5e2b"}], "last": [], "noMoreReplies": true}, "images": [], "id": 93311146}, {"postBy": {"location": "\u65b0\u5317\u5e02\u00b7\u53f0\u7063", "utc": 1532867203000, "level": 0, "avatar": "http://filestoresg1.beetalkmobile.com:8081/file/-5375587089912709742", "name": "\u5c24\u5c0f\u7d05"}, "content": "\u73fe\u5728\u6d41\u884c \u5dee\u8ddd<br /><br />\u5378\u599d\u5f8c\u518d\u4f86\u8aaa<br />", "urls": [], "replies": {"first": [{"content": "\u770b\u9019\u60c5\u6cc1\uff0c\u5378\u599d\u5f8c\u61c9\u8a72\u9084\u884c", "reply": "", "id": 58421326, "name": "\u65b9 \u8001\u5e2b"}], "last": [], "noMoreReplies": true}, "images": [], "id": 93397450}, {"postBy": {"location": "\u9ad8\u96c4\u5e02\u00b7\u53f0\u7063", "utc": 1532870705000, "level": 0, "avatar": "http://filestoresg1.beetalkmobile.com:8081/file/-192144049338040637", "name": "\u99ac"}, "content": "\u5316\u599d+ps\u88dd\u7532\u624d\u662f\u91cd\u8981\u7684\ud83d\ude02\ud83d\ude02", "urls": [], "replies": {"first": [{"content": "\u5176\u5be6\uff0c\u6211\u89ba\u5f97\u50f9\u503c\u89c0\u76f8\u8fd1\u6bd4\u8f03\u91cd\u8981\u8036", "reply": "", "id": 58428081, "name": "\u65b9 \u8001\u5e2b"}], "last": [{"content": "\u6211\u662f\u8aaa\u5916\u8868 \u76f8\u8655\u7576\u7136\u662f\u770b\u5225\u65b9\u9762\u56c9~", "reply": "\u65b9 \u8001\u5e2b", "id": 58450153, "name": "\u99ac"}, {"content": "\u78ba\u5be6\u662f", "reply": "\u99ac", "id": 58455749, "name": "\u65b9 \u8001\u5e2b"}], "noMoreReplies": true}, "images": [], "id": 93401460}, {"postBy": {"location": "", "utc": 1532880873000, "level": 0, "avatar": "http://filestoresg1.beetalkmobile.com:8081/file/788814932175075841", "name": "\u4e0d\u5bb9\u5929\u5730"}, "content": "\u5dee13\u6b72\u5c31\u5df2\u7d93\u5f88\u7dca\u7e43\u4e86", "urls": [], "replies": {"first": [{"content": "\u4f60\u4ea4\u5f80\u904e?", "reply": "", "id": 58428083, "name": "\u65b9 \u8001\u5e2b"}], "last": [{"content": "\u5dee\u592a\u591a\u4e5f\u4e0d\u662f\u5f88\u597d\uff0c\u8d70\u4e0d\u4e45\u3002\u3002\u3002", "reply": "\u4e0d\u5bb9\u5929\u5730", "id": 58486510, "name": "\u65b9 \u8001\u5e2b"}, {"content": "\u6211\u4ea4\u904e-12\uff0c\u6211\u7576\u664220", "reply": "", "id": 58675622, "name": "StanleyLin"}], "noMoreReplies": false}, "images": [], "id": 93415512}, {"postBy": {"location": "", "utc": 1533031694000, "level": 0, "avatar": "http://filestoresg1.beetalkmobile.com:8081/file/9064564094576148114", "name": "Bobby \u91d1\u00d75"}, "content": "\u7537\u7684\u624d15\u6b72\u5c31\u9577\u9019\u6a23\uff01\u592a\u53ef\u6190\u4e86", "urls": [], "replies": {"first": [], "last": [], "noMoreReplies": true}, "images": [], "id": 93540395}, {"postBy": {"location": "\u53f0\u7063", "utc": 1533288410000, "level": 0, "avatar": "http://filestoresg1.beetalkmobile.com:8081/file/3288878973825977345", "name": "\u8001\u7576\u6613\u649e"}, "content": "\u4e00\u65b9\u4e00\u5b9a\u662f\u6709\u9322\u4eba", "urls": [], "replies": {"first": [{"content": "\u53e3\u888b\u6df1\u6dfa\u4f86\u6c7a\u5b9a\u662f\u5403\u5af0\u8c46\u8150\uff0c\u9084\u662f\u677f\u8c46\u8150", "reply": "", "id": 58544709, "name": "\u65b9 \u8001\u5e2b"}, {"content": "\u6211\u9023\u8c46\u8150\u90fd\u6c92 ", "reply": "\u65b9 \u8001\u5e2b", "id": 58544796, "name": "\u8001\u7576\u6613\u649e"}], "last": [], "noMoreReplies": true}, "images": [], "id": 93745965}, {"postBy": {"location": "\u53f0\u4e2d\u5e02\u00b7\u53f0\u7063", "utc": 1533392776000, "level": 0, "avatar": "http://filestoresg1.beetalkmobile.com:8081/file/8710262970140461240", "name": "\u9054\u54e5"}, "content": "\u76ee\u524d\u7121\u9055\u548c\u3002\u4f46\u5341\u5e74\u5f8c\u5462\uff1f", "urls": [], "replies": {"first": [{"content": "\u53ea\u80fd\u554f\u7576\u4e8b\u4eba\u4e86\uff01", "reply": "", "id": 58581615, "name": "\u65b9 \u8001\u5e2b"}], "last": [{"content": "\u5169\u5e74\u90fd\u61f7\u7591\u4e86\uff0c\u9084\u5341\u5e74\u2026\u2026?", "reply": "", "id": 58707178, "name": "Amy"}, {"content": "\u73fe\u5728\u7684\u60c5\u611b\u3002\u90fd\u7d93\u4e0d\u8d77\u8003\u9a57\u3002\u5475\u5475\uff01", "reply": "", "id": 58707449, "name": "\u9054\u54e5"}], "noMoreReplies": true}, "images": [], "id": 93833128}, {"postBy": {"location": "\u53f0\u7063", "utc": 1534078706000, "level": 0, "avatar": "http://filestoresg1.beetalkmobile.com:8081/file/1284310953100307298", "name": "\ud83c\udf53\ud83c\udf44~\u51b0~\ud83c\udf44\ud83c\udf53"}, "content": "\u7167\u7247\u770b\u4e0d\u6e96\uff0c", "urls": [], "replies": {"first": [], "last": [], "noMoreReplies": true}, "images": [], "id": 94414969}, {"postBy": {"location": "\u53f0\u4e2d\u5e02\u00b7\u53f0\u7063", "utc": 1534108863000, "level": 0, "avatar": "http://filestoresg1.beetalkmobile.com:8081/file/9214442909664801315", "name": "\u5b98\u65b9\u8868\u793a:\u6211\u5011\u662f\u901a\u8a0a\u9304"}, "content": "\u6709\u4e00\u7a2e\u6200\u4e0d\u9700\u8981\u52a0\u6cb9~<br /><br /><br /><br /><br /><br /><br /><br /><br /><br /><br /><br /><br /><br /><br /><br />\u4eba\u9b3c\u6200\ud83d\ude10\ud83d\ude10\ud83d\ude10", "urls": [], "replies": {"first": [], "last": [], "noMoreReplies": true}, "images": ["http://filestoresg1.beetalkmobile.com:8081/file/e90478a232b9786194c4286cba3df81d"], "id": 94446551}]}
