{"noMoreComments": true, "cursorEnd": 0, "id": "9283070", "comments": [{"postBy": {"location": "", "utc": 1534323956000, "level": 0, "avatar": "http://filestoresg1.beetalkmobile.com:8081/file/-5383553056890501694", "name": "\u6797\u4f86\u98a8"}, "content": "\ud83d\ude02\ud83d\ude02\ud83d\ude02\u9ad8\u96c4\u4eba<br />\u5728\u96f2\u6797\u5de5\u4f5c", "urls": [], "replies": {"first": [], "last": [], "noMoreReplies": true}, "images": ["http://filestoresg1.beetalkmobile.com:8081/file/87f6411eab2463ef007b3372b1d64c5e"], "id": 94626774}]}
