{"noMoreComments": false, "cursorEnd": 21, "id": "9312103", "comments": [{"postBy": {"location": "\u6843\u5712\u5e02\u00b7\u53f0\u7063", "utc": 1534444932000, "level": 0, "avatar": "http://filestoresg1.beetalkmobile.com:8081/file/-2283712033266751219", "name": "\u85cd\u96f2"}, "content": "\u4e03\u5915\u60c5\u4eba\u7bc0\u5feb\u6a02", "urls": [], "replies": {"first": [], "last": [], "noMoreReplies": true}, "images": [], "id": 94732215}, {"postBy": {"location": "\u6843\u5712\u5e02\u00b7\u53f0\u7063", "utc": 1534445108000, "level": 0, "avatar": "http://filestoresg1.beetalkmobile.com:8081/file/2940404177389658173", "name": "\u958b\u5229"}, "content": "\u60c5\u4eba\u7bc0\u5feb\u6a02\u5537", "urls": [], "replies": {"first": [], "last": [], "noMoreReplies": true}, "images": [], "id": 94732316}, {"postBy": {"location": "\u53f0\u4e2d\u5e02\u00b7\u53f0\u7063", "utc": 1534446839000, "level": 0, "avatar": "http://filestoresg1.beetalkmobile.com:8081/file/8577446342125207956", "name": "James"}, "content": "\u907f\u514d\u88ab\u9583<br />\u8d95\u7dca\u57cb\u5728\u5de5\u4f5c\u5806\u6bd4\u8f03\u597d", "urls": [], "replies": {"first": [], "last": [], "noMoreReplies": true}, "images": [], "id": 94733414}, {"postBy": {"location": "\u53f0\u6771\u7e23\u00b7\u53f0\u7063", "utc": 1534462008000, "level": 0, "avatar": "http://filestoresg1.beetalkmobile.com:8081/file/7353986766514504463", "name": "JyunHao"}, "content": "\u5e78\u6703\u5e78\u6703 \u6211\u4e5f\u662f\u6b38\uff08\u63e1\u624b\ud83e\udd1d", "urls": [], "replies": {"first": [], "last": [], "noMoreReplies": true}, "images": [], "id": 94740469}, {"postBy": {"location": "", "utc": 1534462447000, "level": 0, "avatar": "http://filestoresg1.beetalkmobile.com:8081/file/-506284397273418240", "name": "\u5f35\u5c0f\u80d6"}, "content": "\u4eca\u5929\u4e5f\u662f\u7121\u804a\u6c92\u4e8b\u3002\u8981\u51fa\u4f86\u6643\u6643\u5403\u98ef\u55ce\uff1f", "urls": [], "replies": {"first": [], "last": [], "noMoreReplies": true}, "images": [], "id": 94740741}, {"postBy": {"location": "\u65b0\u5317\u5e02\u00b7\u53f0\u7063", "utc": 1534474520000, "level": 0, "avatar": "http://filestoresg1.beetalkmobile.com:8081/file/-8339041430180827134", "name": "\u79cb\u672c"}, "content": "\u5225\u64d4\u5fc3 \u641e\u4e0d\u597d\u660e\u5e74\u9084\u662f\ud83d\ude0f", "urls": [], "replies": {"first": [], "last": [], "noMoreReplies": true}, "images": [], "id": 94749029}, {"postBy": {"location": "\u65b0\u5317\u5e02\u00b7\u53f0\u7063", "utc": 1534486575000, "level": 0, "avatar": "http://filestoresg1.beetalkmobile.com:8081/file/8748134548941519817", "name": "\u963f\u6587\u513f"}, "content": "+1", "urls": [], "replies": {"first": [], "last": [], "noMoreReplies": true}, "images": [], "id": 94759310}, {"postBy": {"location": "\u9ad8\u96c4\u5e02\u00b7\u53f0\u7063", "utc": 1534487351000, "level": 0, "avatar": "http://filestoresg1.beetalkmobile.com:8081/file/4352708171960165018", "name": "\u2652\u963f\u7acb"}, "content": "+1", "urls": [], "replies": {"first": [], "last": [], "noMoreReplies": true}, "images": [], "id": 94760016}, {"postBy": {"location": "\u65b0\u5317\u5e02\u00b7\u53f0\u7063", "utc": 1534488325000, "level": 0, "avatar": "http://filestoresg1.beetalkmobile.com:8081/file/-2908116993015360884", "name": "\u9ed1\u502b"}, "content": "\u4f60\u7684\u624b\u8ddf\u4f60\u7684\u81c9\u4e0d\u642d\u3002", "urls": [], "replies": {"first": [{"content": "\u5e72\u4f60\u5c41\u4e8b\u6efe\u22ef\u22ef\u6211\u5abd\u751f\u7684", "reply": "", "id": 58921488, "name": "Bella"}], "last": [], "noMoreReplies": true}, "images": [], "id": 94760904}, {"postBy": {"location": "\u53f0\u5317\u5e02\u00b7\u53f0\u7063", "utc": 1534489394000, "level": 0, "avatar": "http://filestoresg1.beetalkmobile.com:8081/file/-2739552750695977195", "name": "Yen"}, "content": "\u4e03\u5915\u7bc0\u5feb\u6a02<br /><br />\u55ae\u8eab\u72d7\u7684\u5b57\u5178\u6c92\u6709\u90a3\u5169\u500b\u5b57\uff38\uff30", "urls": [], "replies": {"first": [], "last": [], "noMoreReplies": true}, "images": [], "id": 94761793}, {"postBy": {"location": "Yunlin County\u00b7Taiwan", "utc": 1534489451000, "level": 0, "avatar": "http://filestoresg1.beetalkmobile.com:8081/file/4414983391700762728", "name": "\u9d1b\u9d26"}, "content": "\u53ef\u4ee5\u8a8d\u8b58\u55ce", "urls": [], "replies": {"first": [], "last": [], "noMoreReplies": true}, "images": [], "id": 94761844}, {"postBy": {"location": "\u6843\u5712\u5e02\u00b7\u53f0\u7063", "utc": 1534496588000, "level": 0, "avatar": "http://filestoresg1.beetalkmobile.com:8081/file/8944552382338655693", "name": "\u6d2a\u5c0f\u5f18"}, "content": "\u55e8\u59b3\u597d", "urls": [], "replies": {"first": [], "last": [], "noMoreReplies": true}, "images": [], "id": 94768035}, {"postBy": {"location": "\u53f0\u5357\u5e02\u00b7\u53f0\u7063", "utc": 1534503189000, "level": 0, "avatar": "http://filestoresg1.beetalkmobile.com:8081/file/-7410467552686058735", "name": "FENDI HUANG\ud83d\udc95"}, "content": "\u54c8\u56c9 \u80fd\u8207\u4f60\u8a8d\u8b58\u55ce\uff1f\u804a\u804a\u55ce", "urls": [], "replies": {"first": [], "last": [], "noMoreReplies": true}, "images": [], "id": 94773792}, {"postBy": {"location": "\u65b0\u5317\u5e02\u00b7\u53f0\u7063", "utc": 1534506279000, "level": 0, "avatar": "http://filestoresg1.beetalkmobile.com:8081/file/7821692631291390652", "name": "\u4f5b\u7cfb\u7537\u5b69"}, "content": "\u53ef\u4ee5\u628a\u59b3\u7684\u5fc3\u9084\u6709\u672a\u4f86\u4ea4\u7d66\u6211\u55ce\uff1f \u6211\u5011\u7a69\u5b9a\u4ea4\u5f80\uff01", "urls": [], "replies": {"first": [], "last": [], "noMoreReplies": true}, "images": [], "id": 94776561}, {"postBy": {"location": "\u53f0\u7063", "utc": 1534507262000, "level": 0, "avatar": "http://filestoresg1.beetalkmobile.com:8081/file/1", "name": "\u674e\u5c0f\u9f8d"}, "content": "\u4f60\u6c92\u53bb", "urls": [], "replies": {"first": [], "last": [], "noMoreReplies": true}, "images": [], "id": 94777574}, {"postBy": {"location": "\u57fa\u9686\u5e02\u00b7\u53f0\u7063", "utc": 1534508174000, "level": 0, "avatar": "http://filestoresg1.beetalkmobile.com:8081/file/-3596593792993257209", "name": "\u904b\u52d5\u967d\u5149\u5065\u5eb7\u71b1\u8840"}, "content": "\u5225\u6015<br />\u9019\u88e1\u5f88\u591a\u4eba\u966a\u4f60\u904e", "urls": [], "replies": {"first": [], "last": [], "noMoreReplies": true}, "images": [], "id": 94778555}, {"postBy": {"location": "\u53f0\u5317\u5e02\u00b7\u53f0\u7063", "utc": 1534508955000, "level": 0, "avatar": "http://filestoresg1.beetalkmobile.com:8081/file/-7011979270460902181", "name": "aconkimo"}, "content": "\u771f\u597d", "urls": [], "replies": {"first": [], "last": [], "noMoreReplies": true}, "images": [], "id": 94779452}, {"postBy": {"location": "\u53f0\u5317\u5e02\u00b7\u53f0\u7063", "utc": 1534510962000, "level": 0, "avatar": "http://filestoresg1.beetalkmobile.com:8081/file/8958249021596450018", "name": "\u83eb\u712e"}, "content": "\u6211\u79c0\u79c0\uff0c\u8981\u4e0d\u8981\u4e00\u8d77\u804a\u5929", "urls": [], "replies": {"first": [], "last": [], "noMoreReplies": true}, "images": [], "id": 94781838}, {"postBy": {"location": "\u53f0\u7063", "utc": 1534511302000, "level": 0, "avatar": "http://filestoresg1.beetalkmobile.com:8081/file/6723972101655000039", "name": "\u738b\u5b50\u75c5 \u5c0f\u82b1"}, "content": "\u771f\u5de7", "urls": [], "replies": {"first": [], "last": [], "noMoreReplies": true}, "images": [], "id": 94782239}]}
