{"noMoreComments": true, "cursorEnd": 0, "id": "9426259", "comments": [{"postBy": {"location": "\u53f0\u5317\u5e02\u00b7\u53f0\u7063", "utc": 1535471211000, "level": 0, "avatar": "http://filestoresg1.beetalkmobile.com:8081/file/6423984658882098439", "name": "\u4ee5\u79ae\u5f85\u4eba\uff0c\u4ee5\u8aa0\u5c0d\u4eba"}, "content": "\u6b61\u8fce", "urls": [], "replies": {"first": [{"content": "\u4f60\u597d", "reply": "", "id": 59244383, "name": "Hu kai"}], "last": [{"content": "\u53f0\u4e2d\u5e25\u54e5\u5537", "reply": "", "id": 59244449, "name": "\u4ee5\u79ae\u5f85\u4eba\uff0c\u4ee5\u8aa0\u5c0d\u4eba"}, {"content": "\u53f0\u5317\u6bd4\u8f03\u5e25", "reply": "", "id": 59246923, "name": "Hu kai"}], "noMoreReplies": true}, "images": [], "id": 95609650}]}
