{"noMoreComments": true, "cursorEnd": 0, "id": "9292567", "comments": [{"postBy": {"location": "\u9ad8\u96c4\u5e02\u00b7\u53f0\u7063", "utc": 1534263755000, "level": 0, "avatar": "http://filestoresg1.beetalkmobile.com:8081/file/4413011989116294285", "name": "\u738b\u656c\u5eb8"}, "content": "\u6211\u5f9e\u5c0f\u6d6a\u8cbb\u5230\u73fe\u5728\u4e5f40\u591a\u5e74\u4e86 \u4e5f\u9ebb\u75fa\u8ddf\u770b\u958b\u4e86", "urls": [], "replies": {"first": [], "last": [], "noMoreReplies": true}, "images": [], "id": 94583996}, {"postBy": {"location": "\u53f0\u5357\u5e02\u00b7\u53f0\u7063", "utc": 1534266421000, "level": 0, "avatar": "http://filestoresg1.beetalkmobile.com:8081/file/3489781761209377148", "name": "Jason"}, "content": "\u5225\u5f8c\u6094\uff0c\u4e00\u5207\u90fd\u9084\u4f86\u5f97\u53ca\u7684", "urls": [], "replies": {"first": [], "last": [], "noMoreReplies": true}, "images": [], "id": 94586785}, {"postBy": {"location": "Taoyuan City\u00b7Taiwan", "utc": 1535856910000, "level": 0, "avatar": "http://filestoresg1.beetalkmobile.com:8081/file/5173287996111799367", "name": "YingHao"}, "content": "\u53ef\u4ee5\u8aaa\u662f\u4eba\u751f\u5982\u6232\u3002\u6232\u5982\u4eba\u751f<br />\u5662\u3002", "urls": [], "replies": {"first": [], "last": [], "noMoreReplies": true}, "images": [], "id": 95911189}, {"postBy": {"location": "\u9ad8\u96c4\u5e02\u00b7\u53f0\u7063", "utc": 1536147122000, "level": 0, "avatar": "http://filestoresg1.beetalkmobile.com:8081/file/8108714649296468987", "name": "\u60dc\u798f\u77e5\u7de3"}, "content": "9\u73ed\u53411", "urls": [], "replies": {"first": [], "last": [], "noMoreReplies": true}, "images": [], "id": 96150111}, {"postBy": {"location": "\u65b0\u5317\u5e02\u00b7\u53f0\u7063", "utc": 1536165486000, "level": 0, "avatar": "http://filestoresg1.beetalkmobile.com:8081/file/-7995875033566606429", "name": "\u91d1\u5305\u9280"}, "content": "\ud83d\ude4b\ud83d\ude4b", "urls": [], "replies": {"first": [], "last": [], "noMoreReplies": true}, "images": [], "id": 96171937}]}
