{"noMoreComments": true, "cursorEnd": 0, "id": "9278469", "comments": [{"postBy": {"location": "\u53f0\u4e2d\u5e02\u00b7\u53f0\u7063", "utc": 1534228961000, "level": 0, "avatar": "http://filestoresg1.beetalkmobile.com:8081/file/-5422947477919308956", "name": "\u786c\u8d77\u4f86"}, "content": "\u9019\u500b\u817f\u592a\u7f8e\u4e86", "urls": [], "replies": {"first": [], "last": [], "noMoreReplies": true}, "images": [], "id": 94548076}, {"postBy": {"location": "", "utc": 1534233047000, "level": 0, "avatar": "http://filestoresg1.beetalkmobile.com:8081/file/5725713423494307731", "name": "\u900d\u9059\u611b\u611b"}, "content": "\u6c92\u7528\u5fae\u4fe1 \u53ea\u6709\u81c9\u66f8-\u8cf4-ig....", "urls": [], "replies": {"first": [], "last": [], "noMoreReplies": true}, "images": [], "id": 94551487}, {"postBy": {"location": "\u5609\u7fa9\u5e02\u00b7\u53f0\u7063", "utc": 1534249377000, "level": 0, "avatar": "http://filestoresg1.beetalkmobile.com:8081/file/2", "name": "User blocked"}, "content": "\u817f\u597d\u6027\u611f", "urls": [], "replies": {"first": [], "last": [], "noMoreReplies": true}, "images": [], "id": 94565843}, {"postBy": {"location": "", "utc": 1534263857000, "level": 0, "avatar": "http://filestoresg1.beetalkmobile.com:8081/file/-4507956969456403451", "name": "\u9177\u65af\u62c9"}, "content": "\u804a\u554a", "urls": [], "replies": {"first": [], "last": [], "noMoreReplies": true}, "images": [], "id": 94584109}, {"postBy": {"location": "", "utc": 1534270483000, "level": 0, "avatar": "http://filestoresg1.beetalkmobile.com:8081/file/-215947357599278588", "name": "\u5929\u5929\uff08\u6211\u5011\u4e0d\u4e00\u6a23\uff09"}, "content": "\u4fee\u9577\u7684\u7f8e\u817f\uff0c\u5168\u90e8\u90fd\u7f8e", "urls": [], "replies": {"first": [], "last": [], "noMoreReplies": true}, "images": [], "id": 94590609}, {"postBy": {"location": "", "utc": 1534335093000, "level": 0, "avatar": "http://filestoresg1.beetalkmobile.com:8081/file/5054704542947742465", "name": "\u5510\u264b\ufe0f"}, "content": "\u52a0\u4e86", "urls": [], "replies": {"first": [], "last": [], "noMoreReplies": true}, "images": [], "id": 94636452}, {"postBy": {"location": "\u9ad8\u96c4\u5e02\u00b7\u53f0\u7063", "utc": 1534449452000, "level": 0, "avatar": "http://filestoresg1.beetalkmobile.com:8081/file/-1155340427123165575", "name": "\u963f\u6bdb"}, "content": "\u4e03\u5915\u60c5\u4eba\u7bc0\u5feb\u6a02", "urls": [], "replies": {"first": [], "last": [], "noMoreReplies": true}, "images": [], "id": 94734951}]}
