{"noMoreComments": true, "cursorEnd": 0, "id": "9087709", "comments": [{"postBy": {"location": "Taichung City\u00b7Taiwan", "utc": 1532426653000, "level": 0, "avatar": "http://filestoresg1.beetalkmobile.com:8081/file/3682044546687187948", "name": "\u5922\u4e00\u5834(*\u02d8\ufe36\u02d8*).\uff61.:*\u2661"}, "content": "\u53ef\u4ee5\u4f01\u5716\u4e0d\u8ecc\ud83d\ude02\ud83d\ude02\ud83d\ude02", "urls": [], "replies": {"first": [{"content": "\u771f\u7684\u8d85\u778e\uff0c\u4e0b\u9762\u90a3\u4e9b\u7537\u751f", "reply": "", "id": 58287087, "name": "\u55ef...\u906e\u81c9\u7537\u2122\ufe0f\u00ae\ufe0f\u00a9\ud83e\udd26\u200d\u2642\ufe0f"}], "last": [], "noMoreReplies": true}, "images": [], "id": 93030184}, {"postBy": {"location": "\u53f0\u5317\u5e02\u00b7\u53f0\u7063", "utc": 1532427094000, "level": 0, "avatar": "http://filestoresg1.beetalkmobile.com:8081/file/-3068371890136752623", "name": "Amy"}, "content": "\u6211\u9084\u770b\u904e50\u5e7e\u6b72\u7559\u8a00\u7d66\u5341\u5e7e\u6b72\u7684\uff0c\u9084\u8aaa\u4ec0\u9ebc\u57fa\u56e0\u914d\u7a2e\u512a\u826f<br />MD\u6211\u90fd\u5feb\u5410\u4e86!<br />\u6211\u7684\u5e74\u7d00\u90fd\u5acc\u4ed6\u8001\u4e86<br />\u4ed6\u5c45\u7136\u597d\u610f\u601d\u7559\u8a00\u7d66\u5341\u5e7e\u6b72\u7684\u5973\u751f<br />\u770b\u5230\u5f88\u50bb\u773c<br />\u2026\u2026<br /><br /><br />\u4e0d\u932f<br />\u9019\u7a2e\u771f\u7684\u7121\u6575\u4e86!", "urls": [], "replies": {"first": [{"content": "\u7121\u6575\u5230\u5e95", "reply": "", "id": 58287485, "name": "\u55ef...\u906e\u81c9\u7537\u2122\ufe0f\u00ae\ufe0f\u00a9\ud83e\udd26\u200d\u2642\ufe0f"}], "last": [{"content": "\u5b85\u7537\u5973\u795e\u5e95\u4e0b\u7559\u8a00\u7684\u6c38\u9060\u90a3\u5e7e\u500b\uff0c\u7136\u5f8c\u8001\u982d\u4e0d\u6703\u653e\u7167\u7247\uff0c\u5c31\u662f\u5b57\u5716", "reply": "spawn", "id": 58287849, "name": "Amy"}, {"content": " \u90a3\u500b\u7248\u6211\u6c92\u901b\u904e.......,\u6211\u8001\u5a46\u5728\u65c1\u908a\uff0c\u4e0d\u6562\u53bb\u770b\u8fa3\u59b9......", "reply": "Amy", "id": 58287892, "name": "spawn"}], "noMoreReplies": false}, "images": [], "id": 93030551}, {"postBy": {"location": "\u53f0\u7063", "utc": 1532427695000, "level": 0, "avatar": "http://filestoresg1.beetalkmobile.com:8081/file/545833879779557936", "name": "\u53ea\u60f3\u7d66\u500b\u64c1\u62b1"}, "content": "\u54c8\u5e7c\u9f52\u9867\u773c\u557e", "urls": [], "replies": {"first": [], "last": [], "noMoreReplies": true}, "images": [], "id": 93031035}, {"postBy": {"location": "", "utc": 1532428479000, "level": 0, "avatar": "http://filestoresg1.beetalkmobile.com:8081/file/7215409818332115456", "name": "\u5c39\u55ac\u4f0a"}, "content": "17\u6b72\u22ef\u6211\u90fd\u53ef\u4ee5\u7576\u5979\u7238\u4e86\ud83e\udd26\u200d\u2642\ufe0f\ud83e\udd26\u200d\u2642\ufe0f", "urls": [], "replies": {"first": [], "last": [], "noMoreReplies": true}, "images": [], "id": 93031677}, {"postBy": {"location": "\u6843\u5712\u5e02\u00b7\u53f0\u7063", "utc": 1532430581000, "level": 0, "avatar": "http://filestoresg1.beetalkmobile.com:8081/file/2699166925241361741", "name": "goose"}, "content": "\u9ad8\u4e2d\u751f\u7248\u5f88\u5c11\u53bb\u770b\uff0c\u6a13\u4e3b\u6d89\u7375\u9084\u771f\u5ee3", "urls": [], "replies": {"first": [{"content": "\u4e0d\u7136\u54ea\u4f86\u90a3\u9ebc\u591a\u7684\u9748\u611f\ud83d\ude02", "reply": "", "id": 58288510, "name": "\u55ef...\u906e\u81c9\u7537\u2122\ufe0f\u00ae\ufe0f\u00a9\ud83e\udd26\u200d\u2642\ufe0f"}], "last": [], "noMoreReplies": true}, "images": [], "id": 93033572}, {"postBy": {"location": "\u9ad8\u96c4\u5e02\u00b7\u53f0\u7063", "utc": 1532431971000, "level": 0, "avatar": "http://filestoresg1.beetalkmobile.com:8081/file/-5499717564376939942", "name": "\u677e\u9f20"}, "content": "\u6211\u53ef\u4ee5\u5e6b\u4f60\u63db\u5c3f\u5e03", "urls": [], "replies": {"first": [{"content": "\u4f60\u5168\u8d0f", "reply": "", "id": 58289235, "name": "\u55ef...\u906e\u81c9\u7537\u2122\ufe0f\u00ae\ufe0f\u00a9\ud83e\udd26\u200d\u2642\ufe0f"}], "last": [{"content": "\u4f60\u9165\u4e86\u543c\u3002 \u54c8\u54c8\u54c8\u3002", "reply": "\u55ef...\u906e\u81c9\u7537\u2122\ufe0f\u00ae\ufe0f\u00a9\ud83e\udd26\u200d\u2642\ufe0f", "id": 58291897, "name": "\u677e\u9f20"}, {"content": "\u5df2\u7fa8\u6155~", "reply": "", "id": 58323430, "name": "\u57ce\u5e02\u908a\u7de3\u4eba"}], "noMoreReplies": true}, "images": [], "id": 93034734}, {"postBy": {"location": "\u65b0\u5317\u5e02\u00b7\u53f0\u7063", "utc": 1532508430000, "level": 0, "avatar": "http://filestoresg1.beetalkmobile.com:8081/file/-8114439792077218559", "name": "\u816b\u7684\u7f8e\u7f8e\ud83d\udd76\ufe0f"}, "content": "\u6211\u597d\u50cf\u6709\u770b\u904e\u90a3\u5e7e\u7bc7\uff5e<br /> <br />\u5979\uff1a\u6211\u9019\u7b11\u5bb9\u53ef\u4ee5\u55ce<br />\u6211\uff1a\u5f88\u7325\u7463", "urls": [], "replies": {"first": [], "last": [], "noMoreReplies": true}, "images": [], "id": 93096543}, {"postBy": {"location": "\u65b0\u5317\u5e02\u00b7\u53f0\u7063", "utc": 1532520285000, "level": 0, "avatar": "http://filestoresg1.beetalkmobile.com:8081/file/-3006414427607238917", "name": "\u57ce\u5e02\u908a\u7de3\u4eba"}, "content": "\u662f\u771f\u611b!!!\u6709\u5750\u7262\u7684\u52c7\u6c23\uff0c\u624d\u6562\u8ddf\u672a\u6210\u5e74\u6c42\u611b\u3002<br />\u4e09\u5e74\u8840\u8cfa\uff0c\u6b7b\u5211\u4e0d\u8667\uff0c\u7121\u6065\u7684\u4eba\u5c31\u662f\u9019\u9ebc\u795e\u52c7~~~", "urls": [], "replies": {"first": [{"content": "\u96e3\u602a\u73fe\u5728\u6691\u5047\uff0c\u4e00\u5806\u5931\u8e64\u4eba\u53e3\u5440", "reply": "", "id": 58322313, "name": "\u55ef...\u906e\u81c9\u7537\u2122\ufe0f\u00ae\ufe0f\u00a9\ud83e\udd26\u200d\u2642\ufe0f"}, {"content": "\u6607\u9f8d\u62f3\u516c\u4ed4\u6211\u7b11\u4e86\ud83d\ude02", "reply": "", "id": 58374960, "name": "WEI\u00a9"}], "last": [], "noMoreReplies": true}, "images": ["http://filestoresg1.beetalkmobile.com:8081/file/57e125a10ee1108f9148db8dbcd31feb"], "id": 93106556}, {"postBy": {"location": "\u65b0\u5317\u5e02\u00b7\u53f0\u7063", "utc": 1532525629000, "level": 0, "avatar": "http://filestoresg1.beetalkmobile.com:8081/file/6951024569162514095", "name": "\u6d77\u71d5"}, "content": "\u6211\u6709\u767c\u7968    \u4f60\u6709\u4ec0\u9ebc?", "urls": [], "replies": {"first": [{"content": "\u6211\u6709\u6298\u8b93\u55ae\ud83d\ude02\ud83d\ude02\ud83d\ude02", "reply": "", "id": 58322301, "name": "\u55ef...\u906e\u81c9\u7537\u2122\ufe0f\u00ae\ufe0f\u00a9\ud83e\udd26\u200d\u2642\ufe0f"}, {"content": "\u5565\u6bc0\u3002\u3002\u3002\u4ec0\u9ebc\u6298\u8b93\u55ae?", "reply": "", "id": 58322823, "name": "\u6d77\u71d5"}], "last": [], "noMoreReplies": true}, "images": ["http://filestoresg1.beetalkmobile.com:8081/file/91c9fe98a3891a87b634b32b4fc2c867"], "id": 93112606}, {"postBy": {"location": "\u53f0\u4e2d\u5e02\u00b7\u53f0\u7063", "utc": 1532534926000, "level": 0, "avatar": "http://filestoresg1.beetalkmobile.com:8081/file/7524334107139557157", "name": "\u9038\u6d77\u85cd"}, "content": "\u770b\u5230\u9ed1\u5f71\u7576\u7136\u8981\u5148\u958b\u69cd\uff0c\u4e82\u69cd\u6253\u9ce5\u8aaa\u4e0d\u5b9a\u80fd\u6253\u4e2d<br />\u6253\u5230\u4e09\u6027\u90a3\u5c31\u597d\u73a9\u4e86", "urls": [], "replies": {"first": [{"content": "\u54c7\u9760\uff0c\u592a\u5641\u4e86\u5566", "reply": "", "id": 58333437, "name": "\u55ef...\u906e\u81c9\u7537\u2122\ufe0f\u00ae\ufe0f\u00a9\ud83e\udd26\u200d\u2642\ufe0f"}], "last": [], "noMoreReplies": true}, "images": [], "id": 93124224}, {"postBy": {"location": "\u65b0\u5317\u5e02\u00b7\u53f0\u7063", "utc": 1532548477000, "level": 0, "avatar": "http://filestoresg1.beetalkmobile.com:8081/file/-6707105589704956486", "name": "\u58de\u813e\u6c23\u5c0f\u59d0\ud83d\ude0c\u8b1d\u7c73\u53ef\ud83d\udc96"}, "content": "\u9019\u500b\u597d\uff01\u8b1b\u8a71\u5920\u76f4\u767d\uff01", "urls": [], "replies": {"first": [], "last": [], "noMoreReplies": true}, "images": [], "id": 93135543}, {"postBy": {"location": "\u53f0\u5357\u5e02\u00b7\u53f0\u7063", "utc": 1532785022000, "level": 0, "avatar": "http://filestoresg1.beetalkmobile.com:8081/file/517345534089687734", "name": "\u6e05\u6e05"}, "content": "\u6211\u4e5f\u6709\u7b11\u5bb9\u54e6\uff01", "urls": [], "replies": {"first": [], "last": [], "noMoreReplies": true}, "images": ["http://filestoresg1.beetalkmobile.com:8081/file/4050fcac2325f19e9fc20958d0e0f25b"], "id": 93326935}, {"postBy": {"location": "\u53f0\u5357\u5e02\u00b7\u53f0\u7063", "utc": 1532790826000, "level": 0, "avatar": "http://filestoresg1.beetalkmobile.com:8081/file/-6702945014490595262", "name": "Hyiameins"}, "content": "\u5979\u5011\u53ef\u80fd\u89ba\u5f97\u64a9\u4f60\u96e3\u5982\u767b\u5929<br /><br />\u5148\u800d\u4e00\u5806\u7cbe\u87f2\u885d\u8166\u7684\u7df4\u7df4\u7b49\u7d1a<br /><br />\u5c0f\u5c0f\u7684\u8eab\u9ad4 \u61f7\u8457\u5049\u5927\u7684\u4fe1\u5ff5<br /><br />\u570b\u6c11\u597d\u9752\u5e74 \u5f9e\u5c0f\u505a\u8d77", "urls": [], "replies": {"first": [], "last": [], "noMoreReplies": true}, "images": [], "id": 93334059}, {"postBy": {"location": "\u6843\u5712\u5e02\u00b7\u53f0\u7063", "utc": 1532846618000, "level": 0, "avatar": "http://filestoresg1.beetalkmobile.com:8081/file/-1095014621199533799", "name": "Vonnie"}, "content": "\u4f01\u5716\u660e\u986f\u554a\uff01<br />\u87f2\u4f5c\u795f\ud83d\ude0f\ud83d\ude0f", "urls": [], "replies": {"first": [], "last": [], "noMoreReplies": true}, "images": [], "id": 93377773}]}
