{"noMoreComments": true, "cursorEnd": 0, "id": "9064396", "comments": [{"postBy": {"location": "\u9ad8\u96c4\u5e02\u00b7\u53f0\u7063", "utc": 1532408985000, "level": 0, "avatar": "http://filestoresg1.beetalkmobile.com:8081/file/-4591743069570333983", "name": "wenchinghuang"}, "content": "\u5973\u4e3b\u662fmasaru\u55ce\uff1f", "urls": [], "replies": {"first": [{"content": "\u4e0d\u662f", "reply": "", "id": 58310696, "name": "D@vid"}], "last": [{"content": "\u4e86\u89e3\uff0c\u611f\u8b1d\u56de\u8986\u3002", "reply": "D@vid", "id": 58310729, "name": "wenchinghuang"}, {"content": "\u4e0d\u5ba2\u6c23", "reply": "wenchinghuang", "id": 58320309, "name": "D@vid"}], "noMoreReplies": true}, "images": [], "id": 93015619}]}
