{"noMoreComments": true, "cursorEnd": 0, "id": "9343943", "comments": [{"postBy": {"location": "\u53f0\u7063", "utc": 1534736892000, "level": 0, "avatar": "http://filestoresg1.beetalkmobile.com:8081/file/-4959967320494500073", "name": "\u8cca\u55b5"}, "content": "id:\u5317\u6975\u578b\u7684\u773c\u6dda<br />\u6211\u4e5f\u6c9230\u7b49", "urls": [], "replies": {"first": [{"content": "\u5df2\u52a0\u02ca\u02c7\u02cb", "reply": "", "id": 59001187, "name": "\u767d\u7d19"}], "last": [], "noMoreReplies": true}, "images": [], "id": 94982880}, {"postBy": {"location": "\u6843\u5712\u5e02\u00b7\u53f0\u7063", "utc": 1534737342000, "level": 0, "avatar": "http://filestoresg1.beetalkmobile.com:8081/file/436762311256159233", "name": "\u90b1\u5955\u5609"}, "content": "\u4e00\u8d77\u5440\ud83d\ude33\ud83d\ude33", "urls": [], "replies": {"first": [{"content": "iD..?", "reply": "", "id": 59001206, "name": "\u767d\u7d19"}], "last": [{"content": "\u5df2\u52a0\u02ca\u02c7\u02cb", "reply": "", "id": 59001322, "name": "\u767d\u7d19"}, {"content": "\u8b1d\u8b1d\ud83d\ude33\ud83d\ude33", "reply": "", "id": 59001472, "name": "\u90b1\u5955\u5609"}], "noMoreReplies": false}, "images": [], "id": 94983287}, {"postBy": {"location": "\u65b0\u5317\u5e02\u00b7\u53f0\u7063", "utc": 1534746854000, "level": 0, "avatar": "http://filestoresg1.beetalkmobile.com:8081/file/1199413265257207028", "name": "\u694a\u80d6\u80d6"}, "content": "iD\u6953\u8449\u6230\u53f2", "urls": [], "replies": {"first": [{"content": "\u5df2\u52a0\u02ca\u02c7\u02cb", "reply": "", "id": 59004500, "name": "\u767d\u7d19"}], "last": [], "noMoreReplies": true}, "images": [], "id": 94992349}, {"postBy": {"location": "\u82d7\u6817\u7e23\u00b7\u53f0\u7063", "utc": 1534748966000, "level": 0, "avatar": "http://filestoresg1.beetalkmobile.com:8081/file/-9047523841526872826", "name": "\ud83c\udf83"}, "content": "\u6101\u5fc3\u4e00\u52d5\u4e82\u5982\u7d72<br />+", "urls": [], "replies": {"first": [{"content": "\u5df2\u52a0\u02ca\u02c7\u02cb", "reply": "", "id": 59004552, "name": "\u767d\u7d19"}], "last": [], "noMoreReplies": true}, "images": [], "id": 94994314}, {"postBy": {"location": "\u53f0\u4e2d\u5e02\u00b7\u53f0\u7063", "utc": 1534750611000, "level": 0, "avatar": "http://filestoresg1.beetalkmobile.com:8081/file/-8834750727759554303", "name": "\u4fca\u6bc5\uc900\uc758"}, "content": "wawa \u9019\u96bb\u662f\u5c0f\u865f\u5537", "urls": [], "replies": {"first": [{"content": "\u5df2\u52a0\u02ca\u02c7\u02cb", "reply": "", "id": 59006496, "name": "\u767d\u7d19"}], "last": [], "noMoreReplies": true}, "images": [], "id": 94995686}, {"postBy": {"location": "\u53f0\u5357\u5e02\u00b7\u53f0\u7063", "utc": 1534753916000, "level": 0, "avatar": "http://filestoresg1.beetalkmobile.com:8081/file/5895807850586080904", "name": "\u5c0f\u50bb"}, "content": "++", "urls": [], "replies": {"first": [{"content": "\u8acb\u7559iD \ud83c\udf38", "reply": "", "id": 59006514, "name": "\u767d\u7d19"}], "last": [{"content": "\u5047\u65b0\u93ae\u7684\u5c0f\u50bb  \u9280\u724c\u4e94\u800c\u5df2\u54c8\u54c8", "reply": "", "id": 59006532, "name": "\u5c0f\u50bb"}, {"content": "\u5df2\u52a0\u02ca\u02c7\u02cb", "reply": "\u5c0f\u50bb", "id": 59006591, "name": "\u767d\u7d19"}], "noMoreReplies": true}, "images": [], "id": 94998663}, {"postBy": {"location": "\u53f0\u5357\u5e02\u00b7\u53f0\u7063", "utc": 1534754007000, "level": 0, "avatar": "http://filestoresg1.beetalkmobile.com:8081/file/-570849943446836418", "name": "\u5c0f\u767d\u767d\u767d\u767d"}, "content": "ID:\u5c0f\u767dSiaoBai", "urls": [], "replies": {"first": [{"content": "\u5df2\u52a0\u02ca\u02c7\u02cb", "reply": "", "id": 59006563, "name": "\u767d\u7d19"}], "last": [], "noMoreReplies": true}, "images": [], "id": 94998734}, {"postBy": {"location": "\u53f0\u4e2d\u5e02\u00b7\u53f0\u7063", "utc": 1534755308000, "level": 0, "avatar": "http://filestoresg1.beetalkmobile.com:8081/file/332859578025307658", "name": "0.0"}, "content": "Serenity\u5ba5", "urls": [], "replies": {"first": [], "last": [], "noMoreReplies": true}, "images": [], "id": 94999964}]}
